dualmcu/__init__.py
dualmcu/max1704x.py
dualmcu/pinmap.py
dualmcu/sdcard.py
dualmcu/shield.py
dualmcu/ssd1306.py
dualmcu-0.0.10.dist-info/METADATA
dualmcu-0.0.10.dist-info/WHEEL
dualmcu-0.0.10.dist-info/top_level.txt
dualmcu-0.0.10.dist-info/RECORD
