Metadata-Version: 2.1
Name: dualmcu
Version: 0.0.10
Summary: Library Version 0.0.10 for the DualMCU board now supports the MAX1704X. The previous version included control of the RGB LED, buzzer, SSD1306 OLED display via I2C, and SD card via SPI.
Author: Mrju10
Author-email: name@email.com
License: License
Classifier: Programming Language :: Python
Classifier: Operating System :: OS Independent
